<annotation verified="yes">
    <folder>Annotation</folder>
    <filename>No_mask22.jpg</filename>
    <path>Face_mask-PascalVOC-export/Annotations/No_mask22.jpg</path>
    <source>
        <database>Unknown</database>
    </source>
    <size>
        <width>416</width>
        <height>416</height>
        <depth>3</depth>
    </size>
    <segmented>0</segmented>
    <object>
    <name>No_mask</name>
    <pose>Unspecified</pose>
    <truncated>0</truncated>
    <difficult>0</difficult>
    <bndbox>
        <xmin>65.88235294117646</xmin>
        <ymin>101.17647058823529</ymin>
        <xmax>345.4117647058823</xmax>
        <ymax>400</ymax>
    </bndbox>
</object>
</annotation>
